srautils/__init__.py
srautils/_version.py
srautils/main.py
srautils/src.py
srautils/utils.py
srautils-1.0.1.dist-info/LICENSE
srautils-1.0.1.dist-info/METADATA
srautils-1.0.1.dist-info/WHEEL
srautils-1.0.1.dist-info/entry_points.txt
srautils-1.0.1.dist-info/top_level.txt
srautils-1.0.1.dist-info/RECORD
