Metadata-Version: 2.1
Name: srautils
Version: 1.0.1
Home-page: https://github.com/yodeng/srautils
License: MIT
Requires-Python: >=3.8
License-File: LICENSE
Requires-Dist: lxml
Requires-Dist: cython
Requires-Dist: hget
Requires-Dist: runjob
